setux/managers/common/config.py
setux/managers/common/venv.py
setux/managers/common/file/common.py
setux/managers/common/file/directory.py
setux/managers/common/file/file.py
setux/managers/common/host/kernel.py
setux/managers/common/host/login.py
setux/managers/common/host/net.py
setux/managers/common/host/system.py
setux/managers/common/package/gem.py
setux/managers/common/package/npm.py
setux/managers/common/package/pip.py
setux/managers/common/package/pypi.py
setux/managers/common/user/group.py
setux/managers/common/user/groups.py
setux/managers/common/user/user.py
setux/managers/common/user/user_.py
setux/managers/system/package.py
setux/managers/system/service.py
setux_managers-0.2507.1.dist-info/METADATA
setux_managers-0.2507.1.dist-info/WHEEL
setux_managers-0.2507.1.dist-info/top_level.txt
setux_managers-0.2507.1.dist-info/RECORD
